setup.py
genqrcode/__init__.py
genqrcode/script.py
genqrcode.egg-info/PKG-INFO
genqrcode.egg-info/SOURCES.txt
genqrcode.egg-info/dependency_links.txt
genqrcode.egg-info/requires.txt
genqrcode.egg-info/top_level.txt