Metadata-Version: 2.1
Name: genqrcode
Version: 1.0.3
Summary: Generate QR Codes!
Home-page: https://github.com/Zeroxyoutube/genqrcode
Author: Zeroxyoutube
Author-email: Zeroxyoutube@gmail.com
